{"status":"done","publicPath":"/static","chunks":{"app":[{"name":"app-05f4ec1d117128ffcff2.js","publicPath":"/staticapp-05f4ec1d117128ffcff2.js","path":"C:\\Users\\Shining\\collection\\ceiling-citadel\\ceiling\\static\\app-05f4ec1d117128ffcff2.js"},{"name":"styles/fonts.42d8adfc4d583dccdcbb45e9c1149a9a.css","publicPath":"/staticstyles/fonts.42d8adfc4d583dccdcbb45e9c1149a9a.css","path":"C:\\Users\\Shining\\collection\\ceiling-citadel\\ceiling\\static\\styles\\fonts.42d8adfc4d583dccdcbb45e9c1149a9a.css"},{"name":"styles/app.bb18ab7e62d9418943c639ce9c6c9ee2.css","publicPath":"/staticstyles/app.bb18ab7e62d9418943c639ce9c6c9ee2.css","path":"C:\\Users\\Shining\\collection\\ceiling-citadel\\ceiling\\static\\styles\\app.bb18ab7e62d9418943c639ce9c6c9ee2.css"},{"name":"app-05f4ec1d117128ffcff2.js.map","publicPath":"/staticapp-05f4ec1d117128ffcff2.js.map","path":"C:\\Users\\Shining\\collection\\ceiling-citadel\\ceiling\\static\\app-05f4ec1d117128ffcff2.js.map"},{"name":"styles/fonts.42d8adfc4d583dccdcbb45e9c1149a9a.css.map","publicPath":"/staticstyles/fonts.42d8adfc4d583dccdcbb45e9c1149a9a.css.map","path":"C:\\Users\\Shining\\collection\\ceiling-citadel\\ceiling\\static\\styles\\fonts.42d8adfc4d583dccdcbb45e9c1149a9a.css.map"},{"name":"styles/app.bb18ab7e62d9418943c639ce9c6c9ee2.css.map","publicPath":"/staticstyles/app.bb18ab7e62d9418943c639ce9c6c9ee2.css.map","path":"C:\\Users\\Shining\\collection\\ceiling-citadel\\ceiling\\static\\styles\\app.bb18ab7e62d9418943c639ce9c6c9ee2.css.map"}],"vendor":[{"name":"vendor-05f4ec1d117128ffcff2.js","publicPath":"/staticvendor-05f4ec1d117128ffcff2.js","path":"C:\\Users\\Shining\\collection\\ceiling-citadel\\ceiling\\static\\vendor-05f4ec1d117128ffcff2.js"},{"name":"vendor-05f4ec1d117128ffcff2.js.map","publicPath":"/staticvendor-05f4ec1d117128ffcff2.js.map","path":"C:\\Users\\Shining\\collection\\ceiling-citadel\\ceiling\\static\\vendor-05f4ec1d117128ffcff2.js.map"}]}}